{
    "Meta Data": {
        "1. Information": "Daily Prices (open, high, low, close) and Volumes",
        "2. Symbol": "601186",
        "3. Last Refreshed": "2025-11-05",
        "4. Output Size": "Compact",
        "5. Time Zone": "Asia/Shanghai"
    },
    "Time Series (Daily)": {
        "2024-06-24": {
            "1. buy price": "8.51",
            "2. high": "8.55",
            "3. low": "8.39",
            "4. sell price": "8.43",
            "5. volume": "466368"
        },
        "2024-06-25": {
            "1. buy price": "8.41",
            "2. high": "8.56",
            "3. low": "8.41",
            "4. sell price": "8.46",
            "5. volume": "411148"
        },
        "2024-06-26": {
            "1. buy price": "8.45",
            "2. high": "8.5",
            "3. low": "8.4",
            "4. sell price": "8.47",
            "5. volume": "367246"
        },
        "2024-06-27": {
            "1. buy price": "8.47",
            "2. high": "8.53",
            "3. low": "8.43",
            "4. sell price": "8.46",
            "5. volume": "349136"
        },
        "2024-06-28": {
            "1. buy price": "8.47",
            "2. high": "8.64",
            "3. low": "8.45",
            "4. sell price": "8.57",
            "5. volume": "471307"
        },
        "2024-07-01": {
            "1. buy price": "8.56",
            "2. high": "8.68",
            "3. low": "8.56",
            "4. sell price": "8.67",
            "5. volume": "523056"
        },
        "2024-07-02": {
            "1. buy price": "8.66",
            "2. high": "8.7",
            "3. low": "8.6",
            "4. sell price": "8.65",
            "5. volume": "424466"
        },
        "2024-07-03": {
            "1. buy price": "8.66",
            "2. high": "8.74",
            "3. low": "8.63",
            "4. sell price": "8.65",
            "5. volume": "365598"
        },
        "2024-07-04": {
            "1. buy price": "8.66",
            "2. high": "8.7",
            "3. low": "8.55",
            "4. sell price": "8.57",
            "5. volume": "335306"
        },
        "2024-07-05": {
            "1. buy price": "8.56",
            "2. high": "8.57",
            "3. low": "8.43",
            "4. sell price": "8.47",
            "5. volume": "407576"
        },
        "2024-07-08": {
            "1. buy price": "8.45",
            "2. high": "8.49",
            "3. low": "8.2",
            "4. sell price": "8.23",
            "5. volume": "644252"
        },
        "2024-07-09": {
            "1. buy price": "8.2",
            "2. high": "8.28",
            "3. low": "8.11",
            "4. sell price": "8.27",
            "5. volume": "595771"
        },
        "2024-07-10": {
            "1. buy price": "8.24",
            "2. high": "8.26",
            "3. low": "8.18",
            "4. sell price": "8.18",
            "5. volume": "315884"
        },
        "2024-07-11": {
            "1. buy price": "8.26",
            "2. high": "8.32",
            "3. low": "8.21",
            "4. sell price": "8.3",
            "5. volume": "443899"
        },
        "2024-07-12": {
            "1. buy price": "8.28",
            "2. high": "8.37",
            "3. low": "8.28",
            "4. sell price": "8.31",
            "5. volume": "336803"
        },
        "2024-07-15": {
            "1. buy price": "8.29",
            "2. high": "8.34",
            "3. low": "8.26",
            "4. sell price": "8.32",
            "5. volume": "236989"
        },
        "2024-07-16": {
            "1. buy price": "8.32",
            "2. high": "8.4",
            "3. low": "8.29",
            "4. sell price": "8.39",
            "5. volume": "300496"
        },
        "2024-07-17": {
            "1. buy price": "8.4",
            "2. high": "8.46",
            "3. low": "8.38",
            "4. sell price": "8.45",
            "5. volume": "328444"
        },
        "2024-07-18": {
            "1. buy price": "8.44",
            "2. high": "8.47",
            "3. low": "8.36",
            "4. sell price": "8.46",
            "5. volume": "300663"
        },
        "2024-07-19": {
            "1. buy price": "8.44",
            "2. high": "8.54",
            "3. low": "8.42",
            "4. sell price": "8.53",
            "5. volume": "326317"
        },
        "2024-07-22": {
            "1. buy price": "8.52",
            "2. high": "8.57",
            "3. low": "8.4",
            "4. sell price": "8.51",
            "5. volume": "426359"
        },
        "2024-07-23": {
            "1. buy price": "8.17",
            "2. high": "8.19",
            "3. low": "8.1",
            "4. sell price": "8.1",
            "5. volume": "476625"
        },
        "2024-07-24": {
            "1. buy price": "8.09",
            "2. high": "8.3",
            "3. low": "8.07",
            "4. sell price": "8.22",
            "5. volume": "482087"
        },
        "2024-07-25": {
            "1. buy price": "8.21",
            "2. high": "8.35",
            "3. low": "8.17",
            "4. sell price": "8.18",
            "5. volume": "456335"
        },
        "2024-07-26": {
            "1. buy price": "8.18",
            "2. high": "8.26",
            "3. low": "8.15",
            "4. sell price": "8.22",
            "5. volume": "275303"
        },
        "2024-07-29": {
            "1. buy price": "8.2",
            "2. high": "8.35",
            "3. low": "8.18",
            "4. sell price": "8.33",
            "5. volume": "376305"
        },
        "2024-07-30": {
            "1. buy price": "8.28",
            "2. high": "8.3",
            "3. low": "8.25",
            "4. sell price": "8.28",
            "5. volume": "340838"
        },
        "2024-07-31": {
            "1. buy price": "8.29",
            "2. high": "8.36",
            "3. low": "8.28",
            "4. sell price": "8.35",
            "5. volume": "465452"
        },
        "2024-08-01": {
            "1. buy price": "8.35",
            "2. high": "8.49",
            "3. low": "8.33",
            "4. sell price": "8.42",
            "5. volume": "562361"
        },
        "2024-08-02": {
            "1. buy price": "8.37",
            "2. high": "8.42",
            "3. low": "8.33",
            "4. sell price": "8.34",
            "5. volume": "368397"
        },
        "2024-08-05": {
            "1. buy price": "8.32",
            "2. high": "8.41",
            "3. low": "8.22",
            "4. sell price": "8.22",
            "5. volume": "435337"
        },
        "2024-08-06": {
            "1. buy price": "8.26",
            "2. high": "8.3",
            "3. low": "8.15",
            "4. sell price": "8.24",
            "5. volume": "420798"
        },
        "2024-08-07": {
            "1. buy price": "8.24",
            "2. high": "8.29",
            "3. low": "8.2",
            "4. sell price": "8.2",
            "5. volume": "238899"
        },
        "2024-08-08": {
            "1. buy price": "8.19",
            "2. high": "8.24",
            "3. low": "8.17",
            "4. sell price": "8.19",
            "5. volume": "228501"
        },
        "2024-08-09": {
            "1. buy price": "8.23",
            "2. high": "8.32",
            "3. low": "8.21",
            "4. sell price": "8.26",
            "5. volume": "326230"
        },
        "2024-08-12": {
            "1. buy price": "8.27",
            "2. high": "8.27",
            "3. low": "8.16",
            "4. sell price": "8.17",
            "5. volume": "277311"
        },
        "2024-08-13": {
            "1. buy price": "8.16",
            "2. high": "8.22",
            "3. low": "8.15",
            "4. sell price": "8.21",
            "5. volume": "249847"
        },
        "2024-08-14": {
            "1. buy price": "8.23",
            "2. high": "8.29",
            "3. low": "8.2",
            "4. sell price": "8.25",
            "5. volume": "307640"
        },
        "2024-08-15": {
            "1. buy price": "8.25",
            "2. high": "8.35",
            "3. low": "8.22",
            "4. sell price": "8.33",
            "5. volume": "312520"
        },
        "2024-08-16": {
            "1. buy price": "8.33",
            "2. high": "8.35",
            "3. low": "8.28",
            "4. sell price": "8.33",
            "5. volume": "250103"
        },
        "2024-08-19": {
            "1. buy price": "8.3",
            "2. high": "8.4",
            "3. low": "8.3",
            "4. sell price": "8.38",
            "5. volume": "300571"
        },
        "2024-08-20": {
            "1. buy price": "8.38",
            "2. high": "8.4",
            "3. low": "8.27",
            "4. sell price": "8.31",
            "5. volume": "286837"
        },
        "2024-08-21": {
            "1. buy price": "8.31",
            "2. high": "8.31",
            "3. low": "8.21",
            "4. sell price": "8.25",
            "5. volume": "219038"
        },
        "2024-08-22": {
            "1. buy price": "8.26",
            "2. high": "8.32",
            "3. low": "8.24",
            "4. sell price": "8.29",
            "5. volume": "237340"
        },
        "2024-08-23": {
            "1. buy price": "8.28",
            "2. high": "8.31",
            "3. low": "8.22",
            "4. sell price": "8.27",
            "5. volume": "232196"
        },
        "2024-08-26": {
            "1. buy price": "8.27",
            "2. high": "8.31",
            "3. low": "8.24",
            "4. sell price": "8.3",
            "5. volume": "224365"
        },
        "2024-08-27": {
            "1. buy price": "8.29",
            "2. high": "8.3",
            "3. low": "8.08",
            "4. sell price": "8.11",
            "5. volume": "444364"
        },
        "2024-08-28": {
            "1. buy price": "8.1",
            "2. high": "8.13",
            "3. low": "7.94",
            "4. sell price": "7.97",
            "5. volume": "376674"
        },
        "2024-08-29": {
            "1. buy price": "7.96",
            "2. high": "7.98",
            "3. low": "7.77",
            "4. sell price": "7.79",
            "5. volume": "547619"
        },
        "2024-08-30": {
            "1. buy price": "7.79",
            "2. high": "7.92",
            "3. low": "7.72",
            "4. sell price": "7.86",
            "5. volume": "437467"
        },
        "2024-09-02": {
            "1. buy price": "7.73",
            "2. high": "7.74",
            "3. low": "7.33",
            "4. sell price": "7.37",
            "5. volume": "1135916"
        },
        "2024-09-03": {
            "1. buy price": "7.34",
            "2. high": "7.4",
            "3. low": "7.21",
            "4. sell price": "7.28",
            "5. volume": "707056"
        },
        "2024-09-04": {
            "1. buy price": "7.24",
            "2. high": "7.27",
            "3. low": "7.07",
            "4. sell price": "7.09",
            "5. volume": "669320"
        },
        "2024-09-05": {
            "1. buy price": "7.11",
            "2. high": "7.16",
            "3. low": "7.06",
            "4. sell price": "7.15",
            "5. volume": "456726"
        },
        "2024-09-06": {
            "1. buy price": "7.14",
            "2. high": "7.2",
            "3. low": "7.1",
            "4. sell price": "7.1",
            "5. volume": "361185"
        },
        "2024-09-09": {
            "1. buy price": "7.08",
            "2. high": "7.08",
            "3. low": "6.86",
            "4. sell price": "6.93",
            "5. volume": "733725"
        },
        "2024-09-10": {
            "1. buy price": "6.93",
            "2. high": "6.97",
            "3. low": "6.84",
            "4. sell price": "6.96",
            "5. volume": "373950"
        },
        "2024-09-11": {
            "1. buy price": "6.92",
            "2. high": "6.93",
            "3. low": "6.86",
            "4. sell price": "6.9",
            "5. volume": "266464"
        },
        "2024-09-12": {
            "1. buy price": "6.9",
            "2. high": "6.94",
            "3. low": "6.87",
            "4. sell price": "6.87",
            "5. volume": "225395"
        },
        "2024-09-13": {
            "1. buy price": "6.88",
            "2. high": "6.9",
            "3. low": "6.83",
            "4. sell price": "6.83",
            "5. volume": "263711"
        },
        "2024-09-18": {
            "1. buy price": "6.82",
            "2. high": "6.85",
            "3. low": "6.72",
            "4. sell price": "6.83",
            "5. volume": "355416"
        },
        "2024-09-19": {
            "1. buy price": "6.86",
            "2. high": "6.96",
            "3. low": "6.8",
            "4. sell price": "6.95",
            "5. volume": "427712"
        },
        "2024-09-20": {
            "1. buy price": "6.94",
            "2. high": "6.97",
            "3. low": "6.86",
            "4. sell price": "6.96",
            "5. volume": "331831"
        },
        "2024-09-23": {
            "1. buy price": "6.95",
            "2. high": "7.04",
            "3. low": "6.92",
            "4. sell price": "6.98",
            "5. volume": "284451"
        },
        "2024-09-24": {
            "1. buy price": "7.02",
            "2. high": "7.26",
            "3. low": "7.01",
            "4. sell price": "7.26",
            "5. volume": "668700"
        },
        "2024-09-25": {
            "1. buy price": "7.47",
            "2. high": "7.89",
            "3. low": "7.47",
            "4. sell price": "7.69",
            "5. volume": "1497576"
        },
        "2024-09-26": {
            "1. buy price": "7.62",
            "2. high": "8.05",
            "3. low": "7.59",
            "4. sell price": "8.05",
            "5. volume": "1299401"
        },
        "2024-09-27": {
            "1. buy price": "8.19",
            "2. high": "8.27",
            "3. low": "8.02",
            "4. sell price": "8.2",
            "5. volume": "955394"
        },
        "2024-09-30": {
            "1. buy price": "8.55",
            "2. high": "8.95",
            "3. low": "8.31",
            "4. sell price": "8.91",
            "5. volume": "2297509"
        },
        "2024-10-08": {
            "1. buy price": "9.8",
            "2. high": "9.8",
            "3. low": "9.06",
            "4. sell price": "9.51",
            "5. volume": "2791572"
        },
        "2024-10-09": {
            "1. buy price": "9.35",
            "2. high": "9.35",
            "3. low": "8.71",
            "4. sell price": "8.71",
            "5. volume": "1850457"
        },
        "2024-10-10": {
            "1. buy price": "8.74",
            "2. high": "9.58",
            "3. low": "8.74",
            "4. sell price": "9.58",
            "5. volume": "2863341"
        },
        "2024-10-11": {
            "1. buy price": "9.57",
            "2. high": "9.85",
            "3. low": "9.28",
            "4. sell price": "9.33",
            "5. volume": "3432313"
        },
        "2024-10-14": {
            "1. buy price": "9.37",
            "2. high": "10.09",
            "3. low": "9.37",
            "4. sell price": "9.61",
            "5. volume": "2519242"
        },
        "2024-10-15": {
            "1. buy price": "9.41",
            "2. high": "9.77",
            "3. low": "9.22",
            "4. sell price": "9.23",
            "5. volume": "1707681"
        },
        "2024-10-16": {
            "1. buy price": "9.11",
            "2. high": "9.42",
            "3. low": "9.06",
            "4. sell price": "9.3",
            "5. volume": "1057037"
        },
        "2024-10-17": {
            "1. buy price": "9.3",
            "2. high": "9.36",
            "3. low": "8.95",
            "4. sell price": "8.99",
            "5. volume": "1267673"
        },
        "2024-10-18": {
            "1. buy price": "8.95",
            "2. high": "9.34",
            "3. low": "8.76",
            "4. sell price": "9.21",
            "5. volume": "1301796"
        },
        "2024-10-21": {
            "1. buy price": "9.26",
            "2. high": "9.54",
            "3. low": "9.13",
            "4. sell price": "9.48",
            "5. volume": "1312745"
        },
        "2024-10-22": {
            "1. buy price": "9.41",
            "2. high": "9.46",
            "3. low": "9.32",
            "4. sell price": "9.39",
            "5. volume": "677657"
        },
        "2024-10-23": {
            "1. buy price": "9.37",
            "2. high": "9.73",
            "3. low": "9.36",
            "4. sell price": "9.59",
            "5. volume": "1310324"
        },
        "2024-10-24": {
            "1. buy price": "9.5",
            "2. high": "9.54",
            "3. low": "9.32",
            "4. sell price": "9.37",
            "5. volume": "688378"
        },
        "2024-10-25": {
            "1. buy price": "9.34",
            "2. high": "9.4",
            "3. low": "9.29",
            "4. sell price": "9.37",
            "5. volume": "563781"
        },
        "2024-10-28": {
            "1. buy price": "9.3",
            "2. high": "9.33",
            "3. low": "9.02",
            "4. sell price": "9.24",
            "5. volume": "869627"
        },
        "2024-10-29": {
            "1. buy price": "9.2",
            "2. high": "9.28",
            "3. low": "9.07",
            "4. sell price": "9.08",
            "5. volume": "732431"
        },
        "2024-10-30": {
            "1. buy price": "9.07",
            "2. high": "9.14",
            "3. low": "8.96",
            "4. sell price": "8.97",
            "5. volume": "527787"
        },
        "2024-10-31": {
            "1. buy price": "8.87",
            "2. high": "9.04",
            "3. low": "8.86",
            "4. sell price": "8.93",
            "5. volume": "725701"
        },
        "2024-11-01": {
            "1. buy price": "8.93",
            "2. high": "9.55",
            "3. low": "8.9",
            "4. sell price": "9.21",
            "5. volume": "1691651"
        },
        "2024-11-04": {
            "1. buy price": "9.15",
            "2. high": "9.25",
            "3. low": "9.06",
            "4. sell price": "9.24",
            "5. volume": "714598"
        },
        "2024-11-05": {
            "1. buy price": "9.23",
            "2. high": "9.41",
            "3. low": "9.19",
            "4. sell price": "9.41",
            "5. volume": "1012154"
        },
        "2024-11-06": {
            "1. buy price": "9.41",
            "2. high": "9.58",
            "3. low": "9.33",
            "4. sell price": "9.51",
            "5. volume": "1199283"
        },
        "2024-11-07": {
            "1. buy price": "9.5",
            "2. high": "9.89",
            "3. low": "9.42",
            "4. sell price": "9.89",
            "5. volume": "1589743"
        },
        "2024-11-08": {
            "1. buy price": "9.94",
            "2. high": "9.98",
            "3. low": "9.65",
            "4. sell price": "9.69",
            "5. volume": "1224623"
        },
        "2024-11-11": {
            "1. buy price": "9.61",
            "2. high": "9.75",
            "3. low": "9.43",
            "4. sell price": "9.61",
            "5. volume": "846849"
        },
        "2024-11-12": {
            "1. buy price": "9.55",
            "2. high": "9.76",
            "3. low": "9.5",
            "4. sell price": "9.53",
            "5. volume": "832236"
        },
        "2024-11-13": {
            "1. buy price": "9.46",
            "2. high": "9.79",
            "3. low": "9.45",
            "4. sell price": "9.59",
            "5. volume": "719430"
        },
        "2024-11-14": {
            "1. buy price": "9.59",
            "2. high": "9.65",
            "3. low": "9.4",
            "4. sell price": "9.41",
            "5. volume": "562431"
        },
        "2024-11-15": {
            "1. buy price": "9.4",
            "2. high": "9.55",
            "3. low": "9.37",
            "4. sell price": "9.37",
            "5. volume": "632675"
        },
        "2024-11-18": {
            "1. buy price": "9.86",
            "2. high": "10.31",
            "3. low": "9.71",
            "4. sell price": "10.26",
            "5. volume": "4515870"
        },
        "2024-11-19": {
            "1. buy price": "9.94",
            "2. high": "9.96",
            "3. low": "9.48",
            "4. sell price": "9.64",
            "5. volume": "3460840"
        },
        "2024-11-20": {
            "1. buy price": "9.55",
            "2. high": "9.73",
            "3. low": "9.54",
            "4. sell price": "9.65",
            "5. volume": "1323841"
        },
        "2024-11-21": {
            "1. buy price": "9.6",
            "2. high": "9.74",
            "3. low": "9.51",
            "4. sell price": "9.56",
            "5. volume": "1036789"
        },
        "2024-11-22": {
            "1. buy price": "9.57",
            "2. high": "9.61",
            "3. low": "9.18",
            "4. sell price": "9.19",
            "5. volume": "1335018"
        },
        "2024-11-25": {
            "1. buy price": "9.17",
            "2. high": "9.31",
            "3. low": "9.07",
            "4. sell price": "9.16",
            "5. volume": "825593"
        },
        "2024-11-26": {
            "1. buy price": "9.16",
            "2. high": "9.23",
            "3. low": "9.1",
            "4. sell price": "9.13",
            "5. volume": "424322"
        },
        "2024-11-27": {
            "1. buy price": "9.12",
            "2. high": "9.2",
            "3. low": "9.05",
            "4. sell price": "9.2",
            "5. volume": "542450"
        },
        "2024-11-28": {
            "1. buy price": "9.18",
            "2. high": "9.3",
            "3. low": "9.16",
            "4. sell price": "9.21",
            "5. volume": "578756"
        },
        "2024-11-29": {
            "1. buy price": "9.19",
            "2. high": "9.32",
            "3. low": "9.19",
            "4. sell price": "9.25",
            "5. volume": "570960"
        },
        "2024-12-02": {
            "1. buy price": "9.25",
            "2. high": "9.48",
            "3. low": "9.2",
            "4. sell price": "9.42",
            "5. volume": "929747"
        },
        "2024-12-03": {
            "1. buy price": "9.37",
            "2. high": "9.64",
            "3. low": "9.37",
            "4. sell price": "9.62",
            "5. volume": "1023747"
        },
        "2024-12-04": {
            "1. buy price": "9.57",
            "2. high": "9.61",
            "3. low": "9.45",
            "4. sell price": "9.48",
            "5. volume": "639863"
        },
        "2024-12-05": {
            "1. buy price": "9.45",
            "2. high": "9.64",
            "3. low": "9.44",
            "4. sell price": "9.5",
            "5. volume": "529717"
        },
        "2024-12-06": {
            "1. buy price": "9.5",
            "2. high": "9.59",
            "3. low": "9.48",
            "4. sell price": "9.56",
            "5. volume": "659979"
        },
        "2024-12-09": {
            "1. buy price": "9.52",
            "2. high": "9.53",
            "3. low": "9.34",
            "4. sell price": "9.41",
            "5. volume": "748610"
        },
        "2024-12-10": {
            "1. buy price": "9.68",
            "2. high": "9.68",
            "3. low": "9.4",
            "4. sell price": "9.41",
            "5. volume": "911872"
        },
        "2024-12-11": {
            "1. buy price": "9.39",
            "2. high": "9.46",
            "3. low": "9.36",
            "4. sell price": "9.4",
            "5. volume": "537878"
        },
        "2024-12-12": {
            "1. buy price": "9.41",
            "2. high": "9.42",
            "3. low": "9.31",
            "4. sell price": "9.41",
            "5. volume": "575737"
        },
        "2024-12-13": {
            "1. buy price": "9.36",
            "2. high": "9.37",
            "3. low": "9.17",
            "4. sell price": "9.17",
            "5. volume": "670051"
        },
        "2024-12-16": {
            "1. buy price": "9.17",
            "2. high": "9.23",
            "3. low": "9.1",
            "4. sell price": "9.21",
            "5. volume": "490612"
        },
        "2024-12-17": {
            "1. buy price": "9.22",
            "2. high": "9.25",
            "3. low": "9.13",
            "4. sell price": "9.16",
            "5. volume": "387889"
        },
        "2024-12-18": {
            "1. buy price": "9.41",
            "2. high": "9.57",
            "3. low": "9.3",
            "4. sell price": "9.33",
            "5. volume": "1146030"
        },
        "2024-12-19": {
            "1. buy price": "9.23",
            "2. high": "9.34",
            "3. low": "9.21",
            "4. sell price": "9.31",
            "5. volume": "581631"
        },
        "2024-12-20": {
            "1. buy price": "9.31",
            "2. high": "9.34",
            "3. low": "9.23",
            "4. sell price": "9.24",
            "5. volume": "464869"
        },
        "2024-12-23": {
            "1. buy price": "9.24",
            "2. high": "9.42",
            "3. low": "9.22",
            "4. sell price": "9.32",
            "5. volume": "796997"
        },
        "2024-12-24": {
            "1. buy price": "9.35",
            "2. high": "9.4",
            "3. low": "9.31",
            "4. sell price": "9.39",
            "5. volume": "470057"
        },
        "2024-12-25": {
            "1. buy price": "9.42",
            "2. high": "9.53",
            "3. low": "9.37",
            "4. sell price": "9.45",
            "5. volume": "739505"
        },
        "2024-12-26": {
            "1. buy price": "9.42",
            "2. high": "9.42",
            "3. low": "9.27",
            "4. sell price": "9.3",
            "5. volume": "572312"
        },
        "2024-12-27": {
            "1. buy price": "9.28",
            "2. high": "9.34",
            "3. low": "9.25",
            "4. sell price": "9.32",
            "5. volume": "423349"
        },
        "2024-12-30": {
            "1. buy price": "9.31",
            "2. high": "9.37",
            "3. low": "9.28",
            "4. sell price": "9.35",
            "5. volume": "420674"
        },
        "2024-12-31": {
            "1. buy price": "9.35",
            "2. high": "9.37",
            "3. low": "9.17",
            "4. sell price": "9.17",
            "5. volume": "592565"
        },
        "2025-01-02": {
            "1. buy price": "9.17",
            "2. high": "9.18",
            "3. low": "8.74",
            "4. sell price": "8.79",
            "5. volume": "915408"
        },
        "2025-01-03": {
            "1. buy price": "8.75",
            "2. high": "8.88",
            "3. low": "8.65",
            "4. sell price": "8.68",
            "5. volume": "532656"
        },
        "2025-01-06": {
            "1. buy price": "8.69",
            "2. high": "8.7",
            "3. low": "8.51",
            "4. sell price": "8.66",
            "5. volume": "494229"
        },
        "2025-01-07": {
            "1. buy price": "8.67",
            "2. high": "8.69",
            "3. low": "8.57",
            "4. sell price": "8.68",
            "5. volume": "344503"
        },
        "2025-01-08": {
            "1. buy price": "8.69",
            "2. high": "8.69",
            "3. low": "8.4",
            "4. sell price": "8.57",
            "5. volume": "561115"
        },
        "2025-01-09": {
            "1. buy price": "8.54",
            "2. high": "8.56",
            "3. low": "8.45",
            "4. sell price": "8.48",
            "5. volume": "321665"
        },
        "2025-01-10": {
            "1. buy price": "8.48",
            "2. high": "8.51",
            "3. low": "8.37",
            "4. sell price": "8.37",
            "5. volume": "281144"
        },
        "2025-01-13": {
            "1. buy price": "8.32",
            "2. high": "8.43",
            "3. low": "8.26",
            "4. sell price": "8.37",
            "5. volume": "291346"
        },
        "2025-01-14": {
            "1. buy price": "8.38",
            "2. high": "8.56",
            "3. low": "8.38",
            "4. sell price": "8.54",
            "5. volume": "367886"
        },
        "2025-01-15": {
            "1. buy price": "8.57",
            "2. high": "8.57",
            "3. low": "8.45",
            "4. sell price": "8.48",
            "5. volume": "316027"
        },
        "2025-01-16": {
            "1. buy price": "8.52",
            "2. high": "8.58",
            "3. low": "8.46",
            "4. sell price": "8.52",
            "5. volume": "329217"
        },
        "2025-01-17": {
            "1. buy price": "8.48",
            "2. high": "8.55",
            "3. low": "8.4",
            "4. sell price": "8.52",
            "5. volume": "264764"
        },
        "2025-01-20": {
            "1. buy price": "8.58",
            "2. high": "8.59",
            "3. low": "8.51",
            "4. sell price": "8.52",
            "5. volume": "327012"
        },
        "2025-01-21": {
            "1. buy price": "8.54",
            "2. high": "8.56",
            "3. low": "8.45",
            "4. sell price": "8.46",
            "5. volume": "302669"
        },
        "2025-01-22": {
            "1. buy price": "8.47",
            "2. high": "8.47",
            "3. low": "8.29",
            "4. sell price": "8.34",
            "5. volume": "304597"
        },
        "2025-01-23": {
            "1. buy price": "8.41",
            "2. high": "8.55",
            "3. low": "8.41",
            "4. sell price": "8.47",
            "5. volume": "382865"
        },
        "2025-01-24": {
            "1. buy price": "8.45",
            "2. high": "8.51",
            "3. low": "8.42",
            "4. sell price": "8.5",
            "5. volume": "274734"
        },
        "2025-01-27": {
            "1. buy price": "8.52",
            "2. high": "8.63",
            "3. low": "8.51",
            "4. sell price": "8.54",
            "5. volume": "333864"
        },
        "2025-02-05": {
            "1. buy price": "8.54",
            "2. high": "8.57",
            "3. low": "8.39",
            "4. sell price": "8.42",
            "5. volume": "339654"
        },
        "2025-02-06": {
            "1. buy price": "8.42",
            "2. high": "8.46",
            "3. low": "8.34",
            "4. sell price": "8.45",
            "5. volume": "375687"
        },
        "2025-02-07": {
            "1. buy price": "8.45",
            "2. high": "8.6",
            "3. low": "8.41",
            "4. sell price": "8.55",
            "5. volume": "609117"
        },
        "2025-02-10": {
            "1. buy price": "8.53",
            "2. high": "8.63",
            "3. low": "8.53",
            "4. sell price": "8.57",
            "5. volume": "469140"
        },
        "2025-02-11": {
            "1. buy price": "8.57",
            "2. high": "8.58",
            "3. low": "8.46",
            "4. sell price": "8.51",
            "5. volume": "350529"
        },
        "2025-02-12": {
            "1. buy price": "8.5",
            "2. high": "8.52",
            "3. low": "8.44",
            "4. sell price": "8.52",
            "5. volume": "372783"
        },
        "2025-02-13": {
            "1. buy price": "8.51",
            "2. high": "8.59",
            "3. low": "8.5",
            "4. sell price": "8.53",
            "5. volume": "569809"
        },
        "2025-02-14": {
            "1. buy price": "8.51",
            "2. high": "8.54",
            "3. low": "8.43",
            "4. sell price": "8.51",
            "5. volume": "408671"
        },
        "2025-02-17": {
            "1. buy price": "8.51",
            "2. high": "8.53",
            "3. low": "8.43",
            "4. sell price": "8.5",
            "5. volume": "522806"
        },
        "2025-02-18": {
            "1. buy price": "8.5",
            "2. high": "8.52",
            "3. low": "8.39",
            "4. sell price": "8.4",
            "5. volume": "461152"
        },
        "2025-02-19": {
            "1. buy price": "8.39",
            "2. high": "8.46",
            "3. low": "8.37",
            "4. sell price": "8.42",
            "5. volume": "375815"
        },
        "2025-02-20": {
            "1. buy price": "8.41",
            "2. high": "8.42",
            "3. low": "8.27",
            "4. sell price": "8.28",
            "5. volume": "697504"
        },
        "2025-02-21": {
            "1. buy price": "8.28",
            "2. high": "8.3",
            "3. low": "8.16",
            "4. sell price": "8.25",
            "5. volume": "594813"
        },
        "2025-02-24": {
            "1. buy price": "8.23",
            "2. high": "8.58",
            "3. low": "8.2",
            "4. sell price": "8.51",
            "5. volume": "1031769"
        },
        "2025-02-25": {
            "1. buy price": "8.51",
            "2. high": "8.51",
            "3. low": "8.37",
            "4. sell price": "8.39",
            "5. volume": "479567"
        },
        "2025-02-26": {
            "1. buy price": "8.36",
            "2. high": "8.52",
            "3. low": "8.36",
            "4. sell price": "8.47",
            "5. volume": "420425"
        },
        "2025-02-27": {
            "1. buy price": "8.48",
            "2. high": "8.5",
            "3. low": "8.38",
            "4. sell price": "8.45",
            "5. volume": "420577"
        },
        "2025-02-28": {
            "1. buy price": "8.42",
            "2. high": "8.54",
            "3. low": "8.4",
            "4. sell price": "8.41",
            "5. volume": "604768"
        },
        "2025-03-03": {
            "1. buy price": "8.41",
            "2. high": "8.47",
            "3. low": "8.36",
            "4. sell price": "8.38",
            "5. volume": "443110"
        },
        "2025-03-04": {
            "1. buy price": "8.37",
            "2. high": "8.38",
            "3. low": "8.32",
            "4. sell price": "8.35",
            "5. volume": "293288"
        },
        "2025-03-05": {
            "1. buy price": "8.34",
            "2. high": "8.38",
            "3. low": "8.29",
            "4. sell price": "8.34",
            "5. volume": "348939"
        },
        "2025-03-06": {
            "1. buy price": "8.35",
            "2. high": "8.4",
            "3. low": "8.3",
            "4. sell price": "8.38",
            "5. volume": "384812"
        },
        "2025-03-07": {
            "1. buy price": "8.35",
            "2. high": "8.36",
            "3. low": "8.28",
            "4. sell price": "8.29",
            "5. volume": "357816"
        },
        "2025-03-10": {
            "1. buy price": "8.29",
            "2. high": "8.3",
            "3. low": "8.2",
            "4. sell price": "8.21",
            "5. volume": "382171"
        },
        "2025-03-11": {
            "1. buy price": "8.17",
            "2. high": "8.21",
            "3. low": "8.15",
            "4. sell price": "8.2",
            "5. volume": "330435"
        },
        "2025-03-12": {
            "1. buy price": "8.21",
            "2. high": "8.3",
            "3. low": "8.18",
            "4. sell price": "8.24",
            "5. volume": "344104"
        },
        "2025-03-13": {
            "1. buy price": "8.23",
            "2. high": "8.28",
            "3. low": "8.2",
            "4. sell price": "8.23",
            "5. volume": "305259"
        },
        "2025-03-14": {
            "1. buy price": "8.22",
            "2. high": "8.37",
            "3. low": "8.21",
            "4. sell price": "8.36",
            "5. volume": "595653"
        },
        "2025-03-17": {
            "1. buy price": "8.37",
            "2. high": "8.43",
            "3. low": "8.37",
            "4. sell price": "8.39",
            "5. volume": "398250"
        },
        "2025-03-18": {
            "1. buy price": "8.4",
            "2. high": "8.42",
            "3. low": "8.34",
            "4. sell price": "8.35",
            "5. volume": "291092"
        },
        "2025-03-19": {
            "1. buy price": "8.34",
            "2. high": "8.36",
            "3. low": "8.26",
            "4. sell price": "8.28",
            "5. volume": "366444"
        },
        "2025-03-20": {
            "1. buy price": "8.28",
            "2. high": "8.35",
            "3. low": "8.27",
            "4. sell price": "8.32",
            "5. volume": "314907"
        },
        "2025-03-21": {
            "1. buy price": "8.31",
            "2. high": "8.41",
            "3. low": "8.26",
            "4. sell price": "8.26",
            "5. volume": "491397"
        },
        "2025-03-24": {
            "1. buy price": "8.28",
            "2. high": "8.31",
            "3. low": "8.19",
            "4. sell price": "8.23",
            "5. volume": "341842"
        },
        "2025-03-25": {
            "1. buy price": "8.24",
            "2. high": "8.29",
            "3. low": "8.21",
            "4. sell price": "8.28",
            "5. volume": "293367"
        },
        "2025-03-26": {
            "1. buy price": "8.28",
            "2. high": "8.3",
            "3. low": "8.24",
            "4. sell price": "8.27",
            "5. volume": "271588"
        },
        "2025-03-27": {
            "1. buy price": "8.26",
            "2. high": "8.27",
            "3. low": "8.21",
            "4. sell price": "8.22",
            "5. volume": "307275"
        },
        "2025-03-28": {
            "1. buy price": "8.21",
            "2. high": "8.23",
            "3. low": "8.14",
            "4. sell price": "8.18",
            "5. volume": "352941"
        },
        "2025-03-31": {
            "1. buy price": "8.16",
            "2. high": "8.18",
            "3. low": "7.92",
            "4. sell price": "7.92",
            "5. volume": "639536"
        },
        "2025-04-01": {
            "1. buy price": "7.96",
            "2. high": "8.06",
            "3. low": "7.95",
            "4. sell price": "8.04",
            "5. volume": "396660"
        },
        "2025-04-02": {
            "1. buy price": "8.05",
            "2. high": "8.08",
            "3. low": "8.02",
            "4. sell price": "8.05",
            "5. volume": "214575"
        },
        "2025-04-03": {
            "1. buy price": "8.01",
            "2. high": "8.15",
            "3. low": "7.98",
            "4. sell price": "8.1",
            "5. volume": "302409"
        },
        "2025-04-07": {
            "1. buy price": "7.85",
            "2. high": "7.88",
            "3. low": "7.29",
            "4. sell price": "7.6",
            "5. volume": "980785"
        },
        "2025-04-08": {
            "1. buy price": "7.59",
            "2. high": "8.05",
            "3. low": "7.59",
            "4. sell price": "8.04",
            "5. volume": "1047740"
        },
        "2025-04-09": {
            "1. buy price": "8.03",
            "2. high": "8.13",
            "3. low": "7.87",
            "4. sell price": "8.06",
            "5. volume": "711017"
        },
        "2025-04-10": {
            "1. buy price": "8.11",
            "2. high": "8.11",
            "3. low": "7.98",
            "4. sell price": "8.08",
            "5. volume": "563951"
        },
        "2025-04-11": {
            "1. buy price": "8.07",
            "2. high": "8.1",
            "3. low": "7.96",
            "4. sell price": "8.0",
            "5. volume": "410900"
        },
        "2025-04-14": {
            "1. buy price": "8.01",
            "2. high": "8.02",
            "3. low": "7.97",
            "4. sell price": "7.98",
            "5. volume": "298987"
        },
        "2025-04-15": {
            "1. buy price": "7.99",
            "2. high": "7.99",
            "3. low": "7.88",
            "4. sell price": "7.94",
            "5. volume": "284910"
        },
        "2025-04-16": {
            "1. buy price": "7.93",
            "2. high": "8.06",
            "3. low": "7.88",
            "4. sell price": "8.06",
            "5. volume": "461175"
        },
        "2025-04-17": {
            "1. buy price": "8.02",
            "2. high": "8.08",
            "3. low": "8.0",
            "4. sell price": "8.06",
            "5. volume": "256221"
        },
        "2025-04-18": {
            "1. buy price": "8.03",
            "2. high": "8.09",
            "3. low": "8.01",
            "4. sell price": "8.07",
            "5. volume": "194455"
        },
        "2025-04-21": {
            "1. buy price": "8.07",
            "2. high": "8.08",
            "3. low": "8.0",
            "4. sell price": "8.02",
            "5. volume": "240841"
        },
        "2025-04-22": {
            "1. buy price": "8.0",
            "2. high": "8.1",
            "3. low": "8.0",
            "4. sell price": "8.09",
            "5. volume": "291335"
        },
        "2025-04-23": {
            "1. buy price": "8.1",
            "2. high": "8.11",
            "3. low": "8.04",
            "4. sell price": "8.05",
            "5. volume": "234246"
        },
        "2025-04-24": {
            "1. buy price": "8.05",
            "2. high": "8.08",
            "3. low": "8.03",
            "4. sell price": "8.05",
            "5. volume": "171176"
        },
        "2025-04-25": {
            "1. buy price": "8.06",
            "2. high": "8.07",
            "3. low": "8.0",
            "4. sell price": "8.03",
            "5. volume": "281053"
        },
        "2025-04-28": {
            "1. buy price": "8.01",
            "2. high": "8.01",
            "3. low": "7.92",
            "4. sell price": "7.94",
            "5. volume": "269498"
        },
        "2025-04-29": {
            "1. buy price": "7.93",
            "2. high": "7.96",
            "3. low": "7.92",
            "4. sell price": "7.92",
            "5. volume": "191062"
        },
        "2025-04-30": {
            "1. buy price": "7.92",
            "2. high": "7.93",
            "3. low": "7.8",
            "4. sell price": "7.81",
            "5. volume": "456881"
        },
        "2025-05-06": {
            "1. buy price": "7.83",
            "2. high": "7.87",
            "3. low": "7.8",
            "4. sell price": "7.86",
            "5. volume": "371029"
        },
        "2025-05-07": {
            "1. buy price": "7.95",
            "2. high": "7.98",
            "3. low": "7.86",
            "4. sell price": "7.93",
            "5. volume": "428343"
        },
        "2025-05-08": {
            "1. buy price": "7.9",
            "2. high": "7.95",
            "3. low": "7.86",
            "4. sell price": "7.91",
            "5. volume": "260203"
        },
        "2025-05-09": {
            "1. buy price": "7.91",
            "2. high": "7.92",
            "3. low": "7.85",
            "4. sell price": "7.85",
            "5. volume": "266101"
        },
        "2025-05-12": {
            "1. buy price": "7.87",
            "2. high": "7.93",
            "3. low": "7.85",
            "4. sell price": "7.93",
            "5. volume": "298251"
        },
        "2025-05-13": {
            "1. buy price": "7.96",
            "2. high": "8.07",
            "3. low": "7.95",
            "4. sell price": "8.04",
            "5. volume": "568264"
        },
        "2025-05-14": {
            "1. buy price": "8.02",
            "2. high": "8.12",
            "3. low": "7.97",
            "4. sell price": "8.11",
            "5. volume": "473764"
        },
        "2025-05-15": {
            "1. buy price": "8.11",
            "2. high": "8.14",
            "3. low": "8.04",
            "4. sell price": "8.07",
            "5. volume": "355707"
        },
        "2025-05-16": {
            "1. buy price": "8.06",
            "2. high": "8.08",
            "3. low": "7.96",
            "4. sell price": "8.0",
            "5. volume": "361056"
        },
        "2025-05-19": {
            "1. buy price": "7.99",
            "2. high": "7.99",
            "3. low": "7.95",
            "4. sell price": "7.98",
            "5. volume": "203518"
        },
        "2025-05-20": {
            "1. buy price": "7.99",
            "2. high": "8.01",
            "3. low": "7.96",
            "4. sell price": "7.99",
            "5. volume": "238895"
        },
        "2025-05-21": {
            "1. buy price": "8.0",
            "2. high": "8.02",
            "3. low": "7.98",
            "4. sell price": "7.99",
            "5. volume": "174210"
        },
        "2025-05-22": {
            "1. buy price": "7.98",
            "2. high": "7.99",
            "3. low": "7.93",
            "4. sell price": "7.95",
            "5. volume": "210829"
        },
        "2025-05-23": {
            "1. buy price": "7.94",
            "2. high": "7.97",
            "3. low": "7.85",
            "4. sell price": "7.85",
            "5. volume": "284289"
        },
        "2025-05-26": {
            "1. buy price": "7.85",
            "2. high": "7.87",
            "3. low": "7.81",
            "4. sell price": "7.83",
            "5. volume": "256309"
        },
        "2025-05-27": {
            "1. buy price": "7.84",
            "2. high": "7.86",
            "3. low": "7.82",
            "4. sell price": "7.83",
            "5. volume": "184203"
        },
        "2025-05-28": {
            "1. buy price": "7.84",
            "2. high": "7.86",
            "3. low": "7.82",
            "4. sell price": "7.84",
            "5. volume": "183511"
        },
        "2025-05-29": {
            "1. buy price": "7.85",
            "2. high": "7.89",
            "3. low": "7.82",
            "4. sell price": "7.87",
            "5. volume": "193165"
        },
        "2025-05-30": {
            "1. buy price": "7.86",
            "2. high": "7.94",
            "3. low": "7.85",
            "4. sell price": "7.91",
            "5. volume": "253353"
        },
        "2025-06-03": {
            "1. buy price": "7.89",
            "2. high": "7.94",
            "3. low": "7.86",
            "4. sell price": "7.94",
            "5. volume": "217683"
        },
        "2025-06-04": {
            "1. buy price": "7.94",
            "2. high": "7.97",
            "3. low": "7.93",
            "4. sell price": "7.97",
            "5. volume": "198237"
        },
        "2025-06-05": {
            "1. buy price": "7.97",
            "2. high": "8.0",
            "3. low": "7.93",
            "4. sell price": "7.96",
            "5. volume": "235076"
        },
        "2025-06-06": {
            "1. buy price": "7.96",
            "2. high": "8.03",
            "3. low": "7.95",
            "4. sell price": "7.98",
            "5. volume": "276347"
        },
        "2025-06-09": {
            "1. buy price": "7.98",
            "2. high": "8.01",
            "3. low": "7.96",
            "4. sell price": "7.98",
            "5. volume": "235801"
        },
        "2025-06-10": {
            "1. buy price": "7.99",
            "2. high": "8.01",
            "3. low": "7.93",
            "4. sell price": "7.94",
            "5. volume": "295140"
        },
        "2025-06-11": {
            "1. buy price": "7.95",
            "2. high": "8.04",
            "3. low": "7.94",
            "4. sell price": "8.02",
            "5. volume": "292279"
        },
        "2025-06-12": {
            "1. buy price": "8.0",
            "2. high": "8.03",
            "3. low": "7.95",
            "4. sell price": "7.98",
            "5. volume": "195493"
        },
        "2025-06-13": {
            "1. buy price": "7.97",
            "2. high": "7.99",
            "3. low": "7.91",
            "4. sell price": "7.93",
            "5. volume": "308499"
        },
        "2025-06-16": {
            "1. buy price": "7.93",
            "2. high": "7.94",
            "3. low": "7.87",
            "4. sell price": "7.88",
            "5. volume": "336844"
        },
        "2025-06-17": {
            "1. buy price": "7.88",
            "2. high": "7.94",
            "3. low": "7.87",
            "4. sell price": "7.93",
            "5. volume": "218789"
        },
        "2025-06-18": {
            "1. buy price": "7.92",
            "2. high": "7.93",
            "3. low": "7.87",
            "4. sell price": "7.9",
            "5. volume": "163745"
        },
        "2025-06-19": {
            "1. buy price": "7.89",
            "2. high": "7.9",
            "3. low": "7.78",
            "4. sell price": "7.78",
            "5. volume": "328106"
        },
        "2025-06-20": {
            "1. buy price": "7.78",
            "2. high": "7.85",
            "3. low": "7.77",
            "4. sell price": "7.82",
            "5. volume": "177399"
        },
        "2025-06-23": {
            "1. buy price": "7.8",
            "2. high": "7.86",
            "3. low": "7.76",
            "4. sell price": "7.83",
            "5. volume": "246388"
        },
        "2025-06-24": {
            "1. buy price": "7.84",
            "2. high": "8.0",
            "3. low": "7.83",
            "4. sell price": "7.99",
            "5. volume": "482582"
        },
        "2025-06-25": {
            "1. buy price": "7.99",
            "2. high": "8.04",
            "3. low": "7.95",
            "4. sell price": "8.03",
            "5. volume": "376690"
        },
        "2025-06-26": {
            "1. buy price": "8.02",
            "2. high": "8.06",
            "3. low": "8.0",
            "4. sell price": "8.03",
            "5. volume": "336129"
        },
        "2025-06-27": {
            "1. buy price": "8.04",
            "2. high": "8.1",
            "3. low": "8.0",
            "4. sell price": "8.01",
            "5. volume": "372759"
        },
        "2025-06-30": {
            "1. buy price": "8.01",
            "2. high": "8.03",
            "3. low": "7.98",
            "4. sell price": "8.01",
            "5. volume": "253380"
        },
        "2025-07-01": {
            "1. buy price": "8.02",
            "2. high": "8.03",
            "3. low": "7.97",
            "4. sell price": "7.98",
            "5. volume": "224362"
        },
        "2025-07-02": {
            "1. buy price": "7.98",
            "2. high": "8.1",
            "3. low": "7.97",
            "4. sell price": "8.09",
            "5. volume": "435532"
        },
        "2025-07-03": {
            "1. buy price": "8.08",
            "2. high": "8.12",
            "3. low": "8.06",
            "4. sell price": "8.08",
            "5. volume": "253540"
        },
        "2025-07-04": {
            "1. buy price": "8.09",
            "2. high": "8.14",
            "3. low": "8.08",
            "4. sell price": "8.12",
            "5. volume": "307690"
        },
        "2025-07-07": {
            "1. buy price": "8.12",
            "2. high": "8.14",
            "3. low": "8.08",
            "4. sell price": "8.13",
            "5. volume": "225716"
        },
        "2025-07-08": {
            "1. buy price": "8.13",
            "2. high": "8.18",
            "3. low": "8.09",
            "4. sell price": "8.17",
            "5. volume": "351984"
        },
        "2025-07-09": {
            "1. buy price": "8.17",
            "2. high": "8.34",
            "3. low": "8.15",
            "4. sell price": "8.22",
            "5. volume": "608567"
        },
        "2025-07-10": {
            "1. buy price": "8.22",
            "2. high": "8.34",
            "3. low": "8.21",
            "4. sell price": "8.28",
            "5. volume": "494452"
        },
        "2025-07-11": {
            "1. buy price": "8.31",
            "2. high": "8.42",
            "3. low": "8.28",
            "4. sell price": "8.28",
            "5. volume": "748789"
        },
        "2025-07-14": {
            "1. buy price": "8.29",
            "2. high": "8.43",
            "3. low": "8.29",
            "4. sell price": "8.34",
            "5. volume": "541809"
        },
        "2025-07-15": {
            "1. buy price": "8.35",
            "2. high": "8.37",
            "3. low": "8.26",
            "4. sell price": "8.3",
            "5. volume": "382114"
        },
        "2025-07-16": {
            "1. buy price": "8.31",
            "2. high": "8.33",
            "3. low": "8.18",
            "4. sell price": "8.25",
            "5. volume": "481779"
        },
        "2025-07-17": {
            "1. buy price": "8.25",
            "2. high": "8.28",
            "3. low": "8.22",
            "4. sell price": "8.27",
            "5. volume": "302084"
        },
        "2025-07-18": {
            "1. buy price": "8.28",
            "2. high": "8.33",
            "3. low": "8.27",
            "4. sell price": "8.33",
            "5. volume": "343157"
        },
        "2025-07-21": {
            "1. buy price": "8.55",
            "2. high": "8.67",
            "3. low": "8.46",
            "4. sell price": "8.66",
            "5. volume": "1927435"
        },
        "2025-07-22": {
            "1. buy price": "8.48",
            "2. high": "8.81",
            "3. low": "8.26",
            "4. sell price": "8.81",
            "5. volume": "2923978"
        },
        "2025-07-23": {
            "1. buy price": "8.93",
            "2. high": "8.93",
            "3. low": "8.42",
            "4. sell price": "8.43",
            "5. volume": "2288093"
        },
        "2025-07-24": {
            "1. buy price": "8.43",
            "2. high": "8.51",
            "3. low": "8.33",
            "4. sell price": "8.46",
            "5. volume": "1342062"
        },
        "2025-07-25": {
            "1. buy price": "8.43",
            "2. high": "8.44",
            "3. low": "8.24",
            "4. sell price": "8.26",
            "5. volume": "1230185"
        },
        "2025-07-28": {
            "1. buy price": "8.26",
            "2. high": "8.27",
            "3. low": "8.21",
            "4. sell price": "8.22",
            "5. volume": "543455"
        },
        "2025-07-29": {
            "1. buy price": "8.21",
            "2. high": "8.23",
            "3. low": "8.14",
            "4. sell price": "8.18",
            "5. volume": "631310"
        },
        "2025-07-30": {
            "1. buy price": "8.17",
            "2. high": "8.24",
            "3. low": "8.15",
            "4. sell price": "8.18",
            "5. volume": "545650"
        },
        "2025-07-31": {
            "1. buy price": "8.16",
            "2. high": "8.18",
            "3. low": "8.04",
            "4. sell price": "8.06",
            "5. volume": "657806"
        },
        "2025-08-01": {
            "1. buy price": "8.05",
            "2. high": "8.08",
            "3. low": "8.04",
            "4. sell price": "8.06",
            "5. volume": "279311"
        },
        "2025-08-04": {
            "1. buy price": "8.05",
            "2. high": "8.09",
            "3. low": "8.04",
            "4. sell price": "8.08",
            "5. volume": "263025"
        },
        "2025-08-05": {
            "1. buy price": "8.09",
            "2. high": "8.12",
            "3. low": "8.07",
            "4. sell price": "8.12",
            "5. volume": "278786"
        },
        "2025-08-06": {
            "1. buy price": "8.12",
            "2. high": "8.12",
            "3. low": "8.07",
            "4. sell price": "8.1",
            "5. volume": "284467"
        },
        "2025-08-07": {
            "1. buy price": "8.12",
            "2. high": "8.15",
            "3. low": "8.09",
            "4. sell price": "8.1",
            "5. volume": "298463"
        },
        "2025-08-08": {
            "1. buy price": "8.1",
            "2. high": "8.21",
            "3. low": "8.07",
            "4. sell price": "8.21",
            "5. volume": "598483"
        },
        "2025-08-11": {
            "1. buy price": "8.34",
            "2. high": "8.37",
            "3. low": "8.22",
            "4. sell price": "8.23",
            "5. volume": "757900"
        },
        "2025-08-12": {
            "1. buy price": "8.23",
            "2. high": "8.26",
            "3. low": "8.17",
            "4. sell price": "8.2",
            "5. volume": "503598"
        },
        "2025-08-13": {
            "1. buy price": "8.2",
            "2. high": "8.23",
            "3. low": "8.16",
            "4. sell price": "8.17",
            "5. volume": "540015"
        },
        "2025-08-14": {
            "1. buy price": "8.17",
            "2. high": "8.21",
            "3. low": "8.08",
            "4. sell price": "8.09",
            "5. volume": "571565"
        },
        "2025-08-15": {
            "1. buy price": "8.07",
            "2. high": "8.12",
            "3. low": "8.07",
            "4. sell price": "8.09",
            "5. volume": "529891"
        },
        "2025-08-18": {
            "1. buy price": "8.1",
            "2. high": "8.16",
            "3. low": "8.09",
            "4. sell price": "8.11",
            "5. volume": "660862"
        },
        "2025-08-19": {
            "1. buy price": "8.12",
            "2. high": "8.14",
            "3. low": "8.07",
            "4. sell price": "8.09",
            "5. volume": "619316"
        },
        "2025-08-20": {
            "1. buy price": "8.07",
            "2. high": "8.11",
            "3. low": "8.04",
            "4. sell price": "8.11",
            "5. volume": "487600"
        },
        "2025-08-21": {
            "1. buy price": "8.13",
            "2. high": "8.22",
            "3. low": "8.12",
            "4. sell price": "8.18",
            "5. volume": "875299"
        },
        "2025-08-22": {
            "1. buy price": "8.17",
            "2. high": "8.23",
            "3. low": "8.12",
            "4. sell price": "8.23",
            "5. volume": "695497"
        },
        "2025-08-25": {
            "1. buy price": "8.23",
            "2. high": "8.33",
            "3. low": "8.22",
            "4. sell price": "8.32",
            "5. volume": "964529"
        },
        "2025-08-26": {
            "1. buy price": "8.3",
            "2. high": "8.3",
            "3. low": "8.25",
            "4. sell price": "8.26",
            "5. volume": "529473"
        },
        "2025-08-27": {
            "1. buy price": "8.27",
            "2. high": "8.28",
            "3. low": "8.11",
            "4. sell price": "8.11",
            "5. volume": "771119"
        },
        "2025-08-28": {
            "1. buy price": "8.1",
            "2. high": "8.15",
            "3. low": "8.03",
            "4. sell price": "8.13",
            "5. volume": "612793"
        },
        "2025-08-29": {
            "1. buy price": "8.15",
            "2. high": "8.26",
            "3. low": "8.12",
            "4. sell price": "8.13",
            "5. volume": "626864"
        },
        "2025-09-01": {
            "1. buy price": "8.12",
            "2. high": "8.14",
            "3. low": "8.07",
            "4. sell price": "8.09",
            "5. volume": "499485"
        },
        "2025-09-02": {
            "1. buy price": "8.07",
            "2. high": "8.1",
            "3. low": "8.03",
            "4. sell price": "8.07",
            "5. volume": "547009"
        },
        "2025-09-03": {
            "1. buy price": "8.07",
            "2. high": "8.09",
            "3. low": "7.95",
            "4. sell price": "7.99",
            "5. volume": "493298"
        },
        "2025-09-04": {
            "1. buy price": "7.99",
            "2. high": "7.99",
            "3. low": "7.89",
            "4. sell price": "7.94",
            "5. volume": "486535"
        },
        "2025-09-05": {
            "1. buy price": "7.94",
            "2. high": "7.99",
            "3. low": "7.9",
            "4. sell price": "7.97",
            "5. volume": "372337"
        },
        "2025-09-08": {
            "1. buy price": "7.96",
            "2. high": "8.04",
            "3. low": "7.94",
            "4. sell price": "8.03",
            "5. volume": "391978"
        },
        "2025-09-09": {
            "1. buy price": "8.03",
            "2. high": "8.04",
            "3. low": "7.96",
            "4. sell price": "8.0",
            "5. volume": "289383"
        },
        "2025-09-10": {
            "1. buy price": "8.0",
            "2. high": "8.01",
            "3. low": "7.94",
            "4. sell price": "7.97",
            "5. volume": "234960"
        },
        "2025-09-11": {
            "1. buy price": "7.95",
            "2. high": "8.02",
            "3. low": "7.94",
            "4. sell price": "8.02",
            "5. volume": "393629"
        },
        "2025-09-12": {
            "1. buy price": "8.01",
            "2. high": "8.07",
            "3. low": "8.0",
            "4. sell price": "8.02",
            "5. volume": "505462"
        },
        "2025-09-15": {
            "1. buy price": "8.02",
            "2. high": "8.05",
            "3. low": "7.98",
            "4. sell price": "8.02",
            "5. volume": "329799"
        },
        "2025-09-16": {
            "1. buy price": "8.02",
            "2. high": "8.03",
            "3. low": "7.97",
            "4. sell price": "8.02",
            "5. volume": "285791"
        },
        "2025-09-17": {
            "1. buy price": "8.01",
            "2. high": "8.07",
            "3. low": "7.97",
            "4. sell price": "8.06",
            "5. volume": "430510"
        },
        "2025-09-18": {
            "1. buy price": "8.04",
            "2. high": "8.05",
            "3. low": "7.89",
            "4. sell price": "7.92",
            "5. volume": "543659"
        },
        "2025-09-19": {
            "1. buy price": "7.92",
            "2. high": "7.95",
            "3. low": "7.9",
            "4. sell price": "7.93",
            "5. volume": "309951"
        },
        "2025-09-22": {
            "1. buy price": "7.92",
            "2. high": "7.93",
            "3. low": "7.84",
            "4. sell price": "7.87",
            "5. volume": "387568"
        },
        "2025-09-23": {
            "1. buy price": "7.86",
            "2. high": "7.94",
            "3. low": "7.78",
            "4. sell price": "7.92",
            "5. volume": "460698"
        },
        "2025-09-24": {
            "1. buy price": "7.88",
            "2. high": "7.91",
            "3. low": "7.83",
            "4. sell price": "7.87",
            "5. volume": "443576"
        },
        "2025-09-25": {
            "1. buy price": "7.86",
            "2. high": "7.87",
            "3. low": "7.78",
            "4. sell price": "7.78",
            "5. volume": "472935"
        },
        "2025-09-26": {
            "1. buy price": "7.78",
            "2. high": "7.84",
            "3. low": "7.75",
            "4. sell price": "7.8",
            "5. volume": "367413"
        },
        "2025-09-29": {
            "1. buy price": "7.8",
            "2. high": "7.84",
            "3. low": "7.72",
            "4. sell price": "7.82",
            "5. volume": "377771"
        },
        "2025-09-30": {
            "1. buy price": "7.83",
            "2. high": "7.88",
            "3. low": "7.79",
            "4. sell price": "7.85",
            "5. volume": "346238"
        },
        "2025-10-09": {
            "1. buy price": "7.85",
            "2. high": "8.05",
            "3. low": "7.84",
            "4. sell price": "8.05",
            "5. volume": "799243"
        },
        "2025-10-10": {
            "1. buy price": "8.01",
            "2. high": "8.22",
            "3. low": "7.98",
            "4. sell price": "8.14",
            "5. volume": "1071287"
        },
        "2025-10-13": {
            "1. buy price": "8.02",
            "2. high": "8.08",
            "3. low": "7.97",
            "4. sell price": "8.08",
            "5. volume": "677331"
        },
        "2025-10-14": {
            "1. buy price": "8.08",
            "2. high": "8.13",
            "3. low": "8.06",
            "4. sell price": "8.08",
            "5. volume": "544779"
        },
        "2025-10-15": {
            "1. buy price": "8.1",
            "2. high": "8.13",
            "3. low": "8.01",
            "4. sell price": "8.07",
            "5. volume": "490192"
        },
        "2025-10-16": {
            "1. buy price": "8.06",
            "2. high": "8.06",
            "3. low": "8.01",
            "4. sell price": "8.04",
            "5. volume": "382125"
        },
        "2025-10-17": {
            "1. buy price": "8.04",
            "2. high": "8.08",
            "3. low": "7.98",
            "4. sell price": "7.99",
            "5. volume": "442532"
        },
        "2025-10-20": {
            "1. buy price": "8.0",
            "2. high": "8.02",
            "3. low": "7.94",
            "4. sell price": "7.96",
            "5. volume": "356628"
        },
        "2025-10-21": {
            "1. buy price": "7.96",
            "2. high": "8.08",
            "3. low": "7.96",
            "4. sell price": "8.07",
            "5. volume": "528252"
        },
        "2025-10-22": {
            "1. buy price": "8.09",
            "2. high": "8.12",
            "3. low": "8.05",
            "4. sell price": "8.07",
            "5. volume": "411203"
        },
        "2025-10-23": {
            "1. buy price": "8.05",
            "2. high": "8.09",
            "3. low": "8.0",
            "4. sell price": "8.09",
            "5. volume": "376402"
        },
        "2025-10-24": {
            "1. buy price": "8.09",
            "2. high": "8.11",
            "3. low": "8.05",
            "4. sell price": "8.09",
            "5. volume": "416119"
        },
        "2025-10-27": {
            "1. buy price": "8.09",
            "2. high": "8.17",
            "3. low": "8.03",
            "4. sell price": "8.16",
            "5. volume": "664733"
        },
        "2025-10-28": {
            "1. buy price": "8.15",
            "2. high": "8.15",
            "3. low": "8.02",
            "4. sell price": "8.03",
            "5. volume": "542231"
        },
        "2025-10-29": {
            "1. buy price": "8.01",
            "2. high": "8.07",
            "3. low": "7.99",
            "4. sell price": "8.06",
            "5. volume": "453237"
        },
        "2025-10-30": {
            "1. buy price": "8.06",
            "2. high": "8.13",
            "3. low": "8.04",
            "4. sell price": "8.05",
            "5. volume": "472161"
        },
        "2025-10-31": {
            "1. buy price": "8.06",
            "2. high": "8.06",
            "3. low": "7.94",
            "4. sell price": "7.95",
            "5. volume": "675185"
        },
        "2025-11-03": {
            "1. buy price": "7.96",
            "2. high": "8.0",
            "3. low": "7.94",
            "4. sell price": "7.99",
            "5. volume": "307575"
        },
        "2025-11-04": {
            "1. buy price": "7.98",
            "2. high": "8.0",
            "3. low": "7.94",
            "4. sell price": "7.97",
            "5. volume": "366759"
        }
    }
}